README.md
setup.cfg
setup.py
resize/__init__.py
resize/__main__.py
resize/resize.py
resize_image.egg-info/PKG-INFO
resize_image.egg-info/SOURCES.txt
resize_image.egg-info/dependency_links.txt
resize_image.egg-info/entry_points.txt
resize_image.egg-info/requires.txt
resize_image.egg-info/top_level.txt