Metadata-Version: 1.0
Name: resize-image
Version: 0.4.0
Summary: Commandline utility to resize an image.
Home-page: https://github.com/jaymu53/resize-image
Author: Jay Mu
Author-email: me@jaymu.com
License: UNKNOWN
Platform: UNKNOWN
